desert/__init__.py
desert/_make.py
desert/_version.py
desert/exceptions.py
desert/py.typed
desert-2022.9.22.dist-info/AUTHORS.rst
desert-2022.9.22.dist-info/LICENSE
desert-2022.9.22.dist-info/METADATA
desert-2022.9.22.dist-info/WHEEL
desert-2022.9.22.dist-info/top_level.txt
desert-2022.9.22.dist-info/RECORD
