Metadata-Version: 2.1
Name: desert
Version: 2022.9.22
Summary: Deserialize to objects while staying DRY
Home-page: https://github.com/python-desert/desert
Author: Desert contributors
Author-email: python-desert@users.noreply.github.com
Classifier: Development Status :: 3 - Alpha
Classifier: Intended Audience :: Developers
Classifier: License :: OSI Approved :: MIT License
Classifier: Operating System :: Unix
Classifier: Operating System :: POSIX
Classifier: Operating System :: Microsoft :: Windows
Classifier: Programming Language :: Python
Classifier: Programming Language :: Python :: 3
Classifier: Programming Language :: Python :: 3.7
Classifier: Programming Language :: Python :: 3.8
Classifier: Programming Language :: Python :: 3.9
Classifier: Programming Language :: Python :: Implementation :: CPython
Classifier: Programming Language :: Python :: Implementation :: PyPy
Classifier: Topic :: Utilities
Requires-Python: >=3.6
License-File: LICENSE
License-File: AUTHORS.rst
Requires-Dist: marshmallow (>=3.0)
Requires-Dist: attrs
Requires-Dist: typing-inspect
Requires-Dist: dataclasses ; python_version < "3.7"
Provides-Extra: dev
Requires-Dist: coverage ; extra == 'dev'
Requires-Dist: cuvner ; extra == 'dev'
Requires-Dist: marshmallow-enum ; extra == 'dev'
Requires-Dist: marshmallow-union ; extra == 'dev'
Requires-Dist: pytest ; extra == 'dev'
Requires-Dist: pytest-cov ; extra == 'dev'
Requires-Dist: pytest-sphinx ; extra == 'dev'
Requires-Dist: pytest-travis-fold ; extra == 'dev'
Requires-Dist: tox ; extra == 'dev'
Requires-Dist: importlib-metadata ; extra == 'dev'
Requires-Dist: versioneer ; extra == 'dev'
Requires-Dist: black ; extra == 'dev'
Requires-Dist: build ; extra == 'dev'
Requires-Dist: pylint ; extra == 'dev'
Requires-Dist: pex ; extra == 'dev'
Requires-Dist: bump2version ; extra == 'dev'
Requires-Dist: docutils ; extra == 'dev'
Requires-Dist: check-manifest ; extra == 'dev'
Requires-Dist: readme-renderer ; extra == 'dev'
Requires-Dist: pygments ; extra == 'dev'
Requires-Dist: isort ; extra == 'dev'
Requires-Dist: mypy ; extra == 'dev'
Requires-Dist: towncrier ; extra == 'dev'
Requires-Dist: twine ; extra == 'dev'
Requires-Dist: wheel ; extra == 'dev'
Provides-Extra: test
Requires-Dist: coverage ; extra == 'test'
Requires-Dist: cuvner ; extra == 'test'
Requires-Dist: marshmallow-enum ; extra == 'test'
Requires-Dist: marshmallow-union ; extra == 'test'
Requires-Dist: pytest ; extra == 'test'
Requires-Dist: pytest-cov ; extra == 'test'
Requires-Dist: pytest-sphinx ; extra == 'test'
Requires-Dist: pytest-travis-fold ; extra == 'test'
Requires-Dist: tox ; extra == 'test'
Requires-Dist: importlib-metadata ; extra == 'test'
